acgp/__init__.py
acgp/client.py
acgp/config.py
acgp/py.typed
acgp/adapters/__init__.py
acgp/adapters/crewai.py
acgp/adapters/generic.py
acgp/models/__init__.py
acgp/models/data_models.py
acgp/transport/__init__.py
acgp/transport/async_queue.py
acgp/transport/batch_sender.py
acgp/transport/retry.py
acgp/transport/sse_client.py
acgp/utils/__init__.py
acgp/utils/observer_interface.py
acgp/wrapper/__init__.py
acgp/wrapper/agent_protocol.py
acgp/wrapper/agent_wrapper.py
acgp/wrapper/decorator.py
acgp-0.1.4.dist-info/METADATA
acgp-0.1.4.dist-info/WHEEL
acgp-0.1.4.dist-info/licenses/LICENSE
acgp-0.1.4.dist-info/RECORD
