Metadata-Version: 2.4
Name: acgp
Version: 0.1.4
Summary: Agentic Cognitive Governance Protocol - Add AI agent oversight with real-time feedback in 5 lines of code
Project-URL: Homepage, https://meaningstack.com
Project-URL: Documentation, https://github.com/meaningstack/acgp/tree/main/docs
Project-URL: Repository, https://github.com/meaningstack/acgp
Project-URL: Issues, https://github.com/meaningstack/acgp/issues
Project-URL: Changelog, https://github.com/meaningstack/acgp/blob/main/CHANGELOG.md
Author-email: MeaningStack <Admin@meaningstack.com>
Maintainer-email: MeaningStack <Admin@meaningstack.com>
License-Expression: MIT
License-File: LICENSE
Keywords: agents,ai,autogen,cognitive,compliance,crewai,feedback,governance,gpt-researcher,langchain,llm,monitoring,oversight,quality,real-time,sse
Classifier: Development Status :: 4 - Beta
Classifier: Intended Audience :: Developers
Classifier: License :: OSI Approved :: MIT License
Classifier: Operating System :: OS Independent
Classifier: Programming Language :: Python :: 3
Classifier: Programming Language :: Python :: 3.9
Classifier: Programming Language :: Python :: 3.10
Classifier: Programming Language :: Python :: 3.11
Classifier: Programming Language :: Python :: 3.12
Classifier: Programming Language :: Python :: 3.13
Classifier: Topic :: Scientific/Engineering :: Artificial Intelligence
Classifier: Topic :: Software Development :: Libraries :: Python Modules
Classifier: Topic :: System :: Monitoring
Classifier: Typing :: Typed
Requires-Python: >=3.9
Requires-Dist: httpx>=0.25.0
Requires-Dist: pydantic>=2.0.0
Requires-Dist: python-dotenv>=1.0.0
Requires-Dist: pyyaml>=6.0
Provides-Extra: all
Requires-Dist: anthropic>=0.17.0; extra == 'all'
Requires-Dist: crewai>=0.28.0; extra == 'all'
Requires-Dist: langchain>=0.1.0; extra == 'all'
Provides-Extra: anthropic
Requires-Dist: anthropic>=0.17.0; extra == 'anthropic'
Provides-Extra: crewai
Requires-Dist: crewai>=0.28.0; extra == 'crewai'
Provides-Extra: dev
Requires-Dist: black>=23.0.0; extra == 'dev'
Requires-Dist: mypy>=1.0.0; extra == 'dev'
Requires-Dist: pytest-asyncio>=0.21.0; extra == 'dev'
Requires-Dist: pytest-cov>=4.0.0; extra == 'dev'
Requires-Dist: pytest>=7.0.0; extra == 'dev'
Requires-Dist: ruff>=0.1.0; extra == 'dev'
Provides-Extra: langchain
Requires-Dist: langchain>=0.1.0; extra == 'langchain'
